[
  {
    "NAME": "프로젝트 태스크 01",
    "ID": "S11P315106-2",
    "COMMENTS": 4,
    "STATUS": "In Progress"
  },
  {
    "NAME": "프로젝트 태스크 02",
    "ID": "S11P315106-2",
    "COMMENTS": 6,
    "STATUS": "In Progress"
  },
  {
    "NAME": "프로젝트 태스크 03",
    "ID": "S11P315106-2",
    "COMMENTS": 6,
    "STATUS": "In Progress"
  },
  {
    "NAME": "프로젝트 태스크 04",
    "ID": "S11P315106-2",
    "COMMENTS": 2,
    "STATUS": "To Do"
  },
  {
    "NAME": "프로젝트 태스크 05",
    "ID": "S11P315106-2",
    "COMMENTS": 10,
    "STATUS": "To Do"
  },
  {
    "NAME": "프로젝트 태스크 06",
    "ID": "S11P315106-2",
    "COMMENTS": 3,
    "STATUS": "To Do"
  }
]
